govuk_bank_holidays/__init__.py
govuk_bank_holidays/bank-holidays.json
govuk_bank_holidays/bank_holidays.py
govuk_bank_holidays/i18n.py
govuk_bank_holidays/locale/cy/LC_MESSAGES/messages.mo
govuk_bank_holidays/locale/cy/LC_MESSAGES/messages.po
govuk_bank_holidays/locale/en/LC_MESSAGES/messages.mo
govuk_bank_holidays/locale/en/LC_MESSAGES/messages.po
govuk_bank_holidays-0.18.dist-info/licenses/LICENSE.txt
govuk_bank_holidays-0.18.dist-info/METADATA
govuk_bank_holidays-0.18.dist-info/WHEEL
govuk_bank_holidays-0.18.dist-info/top_level.txt
govuk_bank_holidays-0.18.dist-info/RECORD
