Metadata-Version: 2.4
Name: govuk-bank-holidays
Version: 0.18
Summary: Tool to load UK bank holidays from GOV.UK
Home-page: https://github.com/ministryofjustice/govuk-bank-holidays
Author: Ministry of Justice Digital & Technology
Author-email: dev@digital.justice.gov.uk
License: MIT
Keywords: bank holidays,govuk,uk
Classifier: Development Status :: 4 - Beta
Classifier: Intended Audience :: Developers
Classifier: License :: OSI Approved :: MIT License
Classifier: Natural Language :: English
Classifier: Operating System :: OS Independent
Classifier: Programming Language :: Python :: 3
Classifier: Programming Language :: Python :: 3 :: Only
Classifier: Programming Language :: Python :: 3.10
Classifier: Programming Language :: Python :: 3.11
Classifier: Programming Language :: Python :: 3.12
Classifier: Programming Language :: Python :: 3.13
Classifier: Programming Language :: Python :: 3.14
Classifier: Topic :: Software Development :: Libraries :: Python Modules
Requires-Python: >=3.6
License-File: LICENSE.txt
Requires-Dist: requests
Dynamic: license-file
